bludwig/LudwigJob.py
bludwig/__init__.py
bludwig/__main__.py
bludwig/helper.py
bludwig-0.0.6.dist-info/LICENSE
bludwig-0.0.6.dist-info/METADATA
bludwig-0.0.6.dist-info/WHEEL
bludwig-0.0.6.dist-info/entry_points.txt
bludwig-0.0.6.dist-info/top_level.txt
bludwig-0.0.6.dist-info/RECORD
