Metadata-Version: 2.1
Name: bludwig
Version: 0.0.6
Summary: Some helper for Ludwig AI
Author-email: djekra <hopsalla@gmail.com>
License: MIT
Project-URL: Homepage, https://github.com/djekra/bludwig
Classifier: Programming Language :: Python :: 3
Classifier: License :: OSI Approved :: MIT License
Classifier: Operating System :: OS Independent
Requires-Python: >=3.9
License-File: LICENSE
Requires-Dist: pandasklar
Requires-Dist: munch
